{
  "title": "IMG_5456_copy_edited",
  "slug": "img-5456-copy-edited-1073",
  "orientation": "landscape",
  "dimensions": {
    "width": 6000,
    "height": 4000
  },
  "variants": {
    "thumb": "content/collections/the-dad-collective/images/img-5456-copy-edited-1073-thumb.webp",
    "lg": "content/collections/the-dad-collective/images/img-5456-copy-edited-1073-lg.webp"
  },
  "dateTaken": "2026-05-30T20:14:26.000Z",
  "metadata": {
    "cameraMake": "Canon",
    "cameraModel": "Canon EOS 200D",
    "camera": "Canon Canon EOS 200D",
    "lens": "EF-S18-55mm f/4-5.6 IS STM",
    "iso": 100,
    "shutterSpeed": "1/640",
    "aperture": "f/5.6",
    "focalLength": "55mm",
    "dateTaken": "2026-05-30T20:14:26.000Z",
    "software": "RapidRAW"
  }
}